mosmetro/__init__.py
mosmetro/__main__.py
mosmetro/connect.py
mosmetro/gen204.py
mosmetro/session.py
mosmetro/utils.py
mosmetro/providers/__init__.py
mosmetro/providers/base.py
mosmetro/providers/mosmetro.py
mosmetro-0.1.1.dist-info/LICENSE
mosmetro-0.1.1.dist-info/METADATA
mosmetro-0.1.1.dist-info/WHEEL
mosmetro-0.1.1.dist-info/entry_points.txt
mosmetro-0.1.1.dist-info/top_level.txt
mosmetro-0.1.1.dist-info/RECORD
