Metadata-Version: 2.1
Name: mosmetro
Version: 0.1.1
Summary: Скрипт для автоматической авторизации в сетях московского (и не только) общественного транспорта
Home-page: https://github.com/mosmetro-android/mosmetro-python
Author: Dmitry Karikh
Author-email: the.dr.hax@gmail.com
License: GNU GPLv3
Platform: UNKNOWN
Classifier: Environment :: Console
Classifier: Programming Language :: Python :: 3.6
Classifier: Intended Audience :: End Users/Desktop
Classifier: License :: OSI Approved :: GNU General Public License v3 (GPLv3)
Classifier: Topic :: Internet
Classifier: Topic :: Utilities
License-File: LICENSE
Requires-Dist: requests
Requires-Dist: furl
Requires-Dist: user-agent
Requires-Dist: beautifulsoup4
